Metadata-Version: 2.1
Name: mitmtools
Version: 0.0.7
Summary: 通过 mitmproxy 开发的便捷工具包
Home-page: https://github.com/Leviathangk/mitmtools
Author: 郭一会儿
Author-email: 1015295213@qq.com
License: MIT Licence
Keywords: mitmtools
Platform: any
